TauLidarServer/__init__.py
TauLidarServer/__main__.py
TauLidarServer/__version__.py
TauLidarServer/index.html
TauLidarServer/server.py
TauLidarServer/css/loading.css
TauLidarServer/css/spectre-exp.min.css
TauLidarServer/css/spectre-icons.min.css
TauLidarServer/css/spectre.min.css
TauLidarServer/img/tau-logo.svg
TauLidarServer/js/OrbitControls.js
TauLidarServer/js/app.js
TauLidarServer/js/pointsView.js
TauLidarServer/js/three.module.js
TauLidarServer/js/vue.esm-browser.js
TauLidarServer-0.0.7.dist-info/LICENSE
TauLidarServer-0.0.7.dist-info/METADATA
TauLidarServer-0.0.7.dist-info/WHEEL
TauLidarServer-0.0.7.dist-info/top_level.txt
TauLidarServer-0.0.7.dist-info/RECORD
