Metadata-Version: 2.1
Name: TauLidarServer
Version: 0.0.7
Summary: Python package for Tau Studio web application
Home-page: https://github.com/OnionIoT/tau-lidar-server
Author: Onion Corporation
Author-email: hello@onioniot.com
License: MIT
Platform: UNKNOWN
Classifier: Programming Language :: Python :: 3
Classifier: License :: OSI Approved :: MIT License
Classifier: Operating System :: OS Independent
Requires-Python: >=3.7
